pyqurl/__init__.py
pyqurl/core.py
pyqurl/exceptions.py
pyqurl/helpers.py
pyqurl/operations.py
pyqurl/db/ponyorm.py
pyqurl/web/flask.py
pyqurl/web/quart.py
pyqurl-0.2.1.dist-info/METADATA
pyqurl-0.2.1.dist-info/WHEEL
pyqurl-0.2.1.dist-info/licenses/LICENSE
pyqurl-0.2.1.dist-info/RECORD
