Metadata-Version: 2.3
Name: pyqurl
Version: 0.2.1
Summary: Simple query string parser for LHS filtering, sorting and pagination
Project-URL: Homepage, https://github.com/gabriel-schneider/pyqurl
Project-URL: Bug Tracker, https://github.com/gabriel-schneider/pyqurl/issues
Author-email: Gabriel Schneider <gabriel.schneider.almeida@gmail.com>
License: MIT License
License-File: LICENSE
Classifier: License :: OSI Approved :: MIT License
Classifier: Operating System :: OS Independent
Classifier: Programming Language :: Python :: 3
Requires-Python: >=3.7
